[{"username": "GabrielMS"}, {"username": "Georgina_BC"}, {"username": "Isacpeal"}, {"username": ""}, {"username": "Virginia"}, {"username": "DanielGarrido"}, {"username": "asalvany"}, {"username": "Cristian_Marilaf"}, {"username": "CMN"}, {"username": "IE"}, {"username": "MiquelPuPa"}, {"username": "dalmiron"}, {"username": "montsepinel"}, {"username": "Villanueva"}, {"username": "MCantenys"}, {"username": "sescosa"}, {"username": "Ber"}, {"username": "IgnasiSola"}, {"username": "Lara30"}, {"username": "Amanda_Visirius"}, {"username": "Jorgemoraleja007"}, {"username": "laisel"}, {"username": "JRueda"}, {"username": "R1G"}, {"username": "staff"}, {"username": "cbertra1"}, {"username": "manuel-L"}, {"username": "ericguti90"}, {"username": "FerranDexeus"}, {"username": "JeniiDiaz"}, {"username": "Dolors58"}, {"username": "AgusRM"}, {"username": "xavier_sans4"}, {"username": "aFerrer"}, {"username": "aroma3"}, {"username": "sdavilabel"}, {"username": "felipelum"}, {"username": "PauFB"}, {"username": "LaiaPico"}, {"username": "CristianPascual"}, {"username": "MireiaSS"}, {"username": "Su"}, {"username": "Rogerbee"}, {"username": "MRosa"}, {"username": "MangelesMorcillo"}, {"username": "Jribasportella"}, {"username": "christimanta"}, {"username": "nachohosta"}, {"username": "Ribazzo"}, {"username": "MARCOS"}, {"username": "Gazquez"}, {"username": "MarcBC"}, {"username": "madeincatalonia"}, {"username": "dmanjon"}, {"username": "eskalivada"}, {"username": "Rosers"}]